LICENSE.txt
MANIFEST.in
README.md
setup.py
test-noaho.py
noahong.egg-info/PKG-INFO
noahong.egg-info/SOURCES.txt
noahong.egg-info/dependency_links.txt
noahong.egg-info/top_level.txt
src/array-aho.cpp
src/array-aho.h
src/noahong.cpp
src/noahong.pyx
src/noahong_legacy.cpp
src/test-array-aho.cpp