Metadata-Version: 2.1
Name: noahong
Version: 0.11.0
Summary: Fast, non-overlapping simultaneous multiple keyword search
Home-page: https://github.com/clustree/noahong
Author: Jeff Donner
Author-email: jeffrey.donner@gmail.com
License: UNKNOWN
Platform: UNKNOWN
Classifier: Intended Audience :: Developers
Classifier: Intended Audience :: Information Technology
Classifier: License :: OSI Approved :: MIT License
Classifier: Development Status :: 4 - Beta
Classifier: Programming Language :: C++
Classifier: Programming Language :: Cython
Classifier: Programming Language :: Python :: 3
Classifier: Programming Language :: Python :: 3.7
Classifier: Programming Language :: Python :: 3.8
Classifier: Programming Language :: Python :: 3.9
Classifier: Programming Language :: Python :: 3.10
Classifier: Operating System :: OS Independent
Classifier: Environment :: Console
Classifier: Topic :: Text Processing
Requires-Python: >=3.6.*, <4
